LAB1/06_mux/src/mux_4x1.v
module mux_4x1(input wire [3:0] i, input wire [1:0] s, output wire z);
    // Preserve the original lab ordering: 00 -> i[3].
    assign z = i[3-s];
endmodule

LAB1/06_mux/sim/tb_mux_4x1.sv
`timescale 1ns/1ps

module tb_mux_4x1;

    reg [3:0] i;
    reg [1:0] s;
    wire z;

    mux_4x1 dut(i, s, z);

    integer n, checked = 0;
    reg [0:0] expected;

    initial begin
        $dumpfile("wave.vcd");
        $dumpvars(0, tb_mux_4x1);

        for(n = 0; n < 64; n = n + 1) begin
            {i, s} = n;

            expected = ((n / 4) >> (3 - (n % 4))) & 1;

            #10;

            if (z !== expected)
                $fatal(1,
                       "FAIL mux_4x1 vector=%0d expected=%h actual=%h",
                       n, expected, z);

            checked = checked + 1;
        end

        if (checked != 64)
            $fatal(1, "Incomplete test");

        $display("LAB1_PASS mux_4x1 cases=%0d", checked);
        $finish;
    end

    initial begin
        #100000;
        $fatal(1, "Watchdog");
    end

endmodule

evidence/vscode/LAB1/06_mux/normal__run-36f7a5d8e67244aab57bbea64d2a5076/wave.vcd
$date
	Mon Sep 14 03:52:36 2026
$end
$version
	Icarus Verilog
$end
$timescale
	1ps
$end
$scope module tb_mux_4x1 $end
$var wire 1 ! z $end
$var reg 1 " expected $end
$var reg 4 # i [3:0] $end
$var reg 2 $ s [1:0] $end
$var integer 32 % checked [31:0] $end
$var integer 32 & n [31:0] $end
$scope module dut $end
$var wire 4 ' i [3:0] $end
$var wire 2 ( s [1:0] $end
$var wire 1 ! z $end
$upscope $end
$upscope $end
$enddefinitions $end
$comment Show the parameter values. $end
$dumpall
$end
#0
$dumpvars
b0 (
b0 '
b0 &
b0 %
b0 $
b0 #
0"
0!
$end
#10000
b1 $
b1 (
b1 &
b1 %
#20000
b10 $
b10 (
b10 &
b10 %
#30000
b11 $
b11 (
b11 &
b11 %
#40000
b1 #
b1 '
b0 $
b0 (
b100 &
b100 %
#50000
b1 $
b1 (
b101 &
b101 %
#60000
b10 $
b10 (
b110 &
b110 %
#70000
1"
1!
b11 $
b11 (
b111 &
b111 %
#80000
0"
b10 #
b10 '
0!
b0 $
b0 (
b1000 &
b1000 %
#90000
b1 $
b1 (
b1001 &
b1001 %
#100000
1"
1!
b10 $
b10 (
b1010 &
b1010 %
#110000
0"
0!
b11 $
b11 (
b1011 &
b1011 %
#120000
b11 #
b11 '
b0 $
b0 (
b1100 &
b1100 %
#130000
b1 $
b1 (
b1101 &
b1101 %
#140000
1"
1!
b10 $
b10 (
b1110 &
b1110 %
#150000
b11 $
b11 (
b1111 &
b1111 %
#160000
0"
b100 #
b100 '
0!
b0 $
b0 (
b10000 &
b10000 %
#170000
1"
1!
b1 $
b1 (
b10001 &
b10001 %
#180000
0"
0!
b10 $
b10 (
b10010 &
b10010 %
#190000
b11 $
b11 (
b10011 &
b10011 %
#200000
b101 #
b101 '
b0 $
b0 (
b10100 &
b10100 %
#210000
1"
1!
b1 $
b1 (
b10101 &
b10101 %
#220000
0"
0!
b10 $
b10 (
b10110 &
b10110 %
#230000
1"
1!
b11 $
b11 (
b10111 &
b10111 %
#240000
0"
b110 #
b110 '
0!
b0 $
b0 (
b11000 &
b11000 %
#250000
1"
1!
b1 $
b1 (
b11001 &
b11001 %
#260000
b10 $
b10 (
b11010 &
b11010 %
#270000
0"
0!
b11 $
b11 (
b11011 &
b11011 %
#280000
b111 #
b111 '
b0 $
b0 (
b11100 &
b11100 %
#290000
1"
1!
b1 $
b1 (
b11101 &
b11101 %
#300000
b10 $
b10 (
b11110 &
b11110 %
#310000
b11 $
b11 (
b11111 &
b11111 %
#320000
b1000 #
b1000 '
1!
b0 $
b0 (
b100000 &
b100000 %
#330000
0"
0!
b1 $
b1 (
b100001 &
b100001 %
#340000
b10 $
b10 (
b100010 &
b100010 %
#350000
b11 $
b11 (
b100011 &
b100011 %
#360000
1"
b1001 #
b1001 '
1!
b0 $
b0 (
b100100 &
b100100 %
#370000
0"
0!
b1 $
b1 (
b100101 &
b100101 %
#380000
b10 $
b10 (
b100110 &
b100110 %
#390000
1"
1!
b11 $
b11 (
b100111 &
b100111 %
#400000
b1010 #
b1010 '
b0 $
b0 (
b101000 &
b101000 %
#410000
0"
0!
b1 $
b1 (
b101001 &
b101001 %
#420000
1"
1!
b10 $
b10 (
b101010 &
b101010 %
#430000
0"
0!
b11 $
b11 (
b101011 &
b101011 %
#440000
1"
b1011 #
b1011 '
1!
b0 $
b0 (
b101100 &
b101100 %
#450000
0"
0!
b1 $
b1 (
b101101 &
b101101 %
#460000
1"
1!
b10 $
b10 (
b101110 &
b101110 %
#470000
b11 $
b11 (
b101111 &
b101111 %
#480000
b1100 #
b1100 '
b0 $
b0 (
b110000 &
b110000 %
#490000
b1 $
b1 (
b110001 &
b110001 %
#500000
0"
0!
b10 $
b10 (
b110010 &
b110010 %
#510000
b11 $
b11 (
b110011 &
b110011 %
#520000
1"
b1101 #
b1101 '
1!
b0 $
b0 (
b110100 &
b110100 %
#530000
b1 $
b1 (
b110101 &
b110101 %
#540000
0"
0!
b10 $
b10 (
b110110 &
b110110 %
#550000
1"
1!
b11 $
b11 (
b110111 &
b110111 %
#560000
b1110 #
b1110 '
b0 $
b0 (
b111000 &
b111000 %
#570000
b1 $
b1 (
b111001 &
b111001 %
#580000
b10 $
b10 (
b111010 &
b111010 %
#590000
0"
0!
b11 $
b11 (
b111011 &
b111011 %
#600000
1"
b1111 #
b1111 '
1!
b0 $
b0 (
b111100 &
b111100 %
#610000
b1 $
b1 (
b111101 &
b111101 %
#620000
b10 $
b10 (
b111110 &
b111110 %
#630000
b11 $
b11 (
b111111 &
b111111 %
#640000
b1000000 &
b1000000 %
